mixd/__init__.py
mixd/cloudflared.py
mixd/handler.py
mixd/main.py
mixd/server.py
mixd/utils.py
mixd-1.2.dist-info/METADATA
mixd-1.2.dist-info/WHEEL
mixd-1.2.dist-info/entry_points.txt
mixd-1.2.dist-info/top_level.txt
mixd-1.2.dist-info/RECORD
