Metadata-Version: 2.4
Name: mixd
Version: 1.2
Summary: Dev HTTPS server with optional Cloudflared tunnel
Home-page: https://github.com/yourusername/mixd
Author: mixddev
Classifier: Programming Language :: Python :: 3
Classifier: License :: OSI Approved :: MIT License
Classifier: Operating System :: OS Independent
Requires-Python: >=3.7
Requires-Dist: rich
Dynamic: author
Dynamic: classifier
Dynamic: description
Dynamic: description-content-type
Dynamic: home-page
Dynamic: requires-dist
Dynamic: requires-python
Dynamic: summary
